src/decentralized-p2p/__init__.py
src/decentralized-p2p/peer.py
src/decentralized-p2p/signature.py
decentralized_p2p-0.0.2.dist-info/METADATA
decentralized_p2p-0.0.2.dist-info/WHEEL
decentralized_p2p-0.0.2.dist-info/licenses/LICENSE
decentralized_p2p-0.0.2.dist-info/RECORD
