Metadata-Version: 2.1
Name: decentralized-p2p
Version: 0.0.2
Summary: A small package built for my cs50p course. It includes a Peer module which provides straight forward methods to exchange messages and create/join networks
Project-URL: Homepage, https://github.com/NeekoKun/cs50p-project
Project-URL: Bug Tracker, https://github.com/NeekoKun/cs50p-project/issues
Author-email: NeekoKun <leonardo.riccim@gmail.com>
License-File: LICENSE
Classifier: License :: OSI Approved :: MIT License
Classifier: Operating System :: OS Independent
Classifier: Programming Language :: Python :: 3
Requires-Python: >=3.7
